mymusic_dl/__init__.py
mymusic_dl/functions.py
mymusic_dl/main.py
mymusic_dl-0.0.1a7.dist-info/LICENSE
mymusic_dl-0.0.1a7.dist-info/METADATA
mymusic_dl-0.0.1a7.dist-info/WHEEL
mymusic_dl-0.0.1a7.dist-info/entry_points.txt
mymusic_dl-0.0.1a7.dist-info/top_level.txt
mymusic_dl-0.0.1a7.dist-info/RECORD
