Metadata-Version: 2.1
Name: mymusic-dl
Version: 0.0.1a7
Summary: Download your music playlists using web-scraping and youtube-dl no API keys involved
Home-page: https://github.com/pr0PM/mymusic-dl/
Author: Prateek Mishra
Author-email: pr0pm@pm.me
License: MIT
Keywords: music download youtube spotify playlist
Platform: UNKNOWN
Classifier: Development Status :: 3 - Alpha
Classifier: License :: OSI Approved :: MIT License
Classifier: Operating System :: POSIX
Classifier: Operating System :: OS Independent
Classifier: Topic :: Utilities
Classifier: Topic :: Internet
Classifier: Topic :: Multimedia
Classifier: Topic :: Multimedia :: Sound/Audio
Classifier: Intended Audience :: End Users/Desktop
Requires-Python: >=3
Requires-Dist: requests (>=2.22.0)
Requires-Dist: youtube-dl (>=2020.6.16.1)
Requires-Dist: beautifulsoup4 (>=4.9.3)
